src/__init__.py
src/data_object.py
src/database.py
src/stress_test.py
src/vector_db.py
src/word_generator.py
tests/__init__.py
PyVecDB-0.1.2.dist-info/METADATA
PyVecDB-0.1.2.dist-info/WHEEL
PyVecDB-0.1.2.dist-info/top_level.txt
PyVecDB-0.1.2.dist-info/RECORD
