Metadata-Version: 2.1
Name: PyVecDB
Version: 0.1.2
Summary: A Python library for efficient similarity search using high-dimensional vectors.
Home-page: https://github.com/tyronenorth/PyVecDB
Author: Your Name
Author-email: north.tyronejr@gmail.com
License: UNKNOWN
Platform: UNKNOWN
Classifier: Development Status :: 3 - Alpha
Classifier: Intended Audience :: Developers
Classifier: License :: OSI Approved :: MIT License
Classifier: Programming Language :: Python :: 3
Classifier: Programming Language :: Python :: 3.6
Classifier: Programming Language :: Python :: 3.7
Classifier: Programming Language :: Python :: 3.8
Classifier: Programming Language :: Python :: 3.9
Requires-Dist: annoy
Requires-Dist: msgpack
